{"cameraMode":{"drawMode":0,"name":"Shaded","section":"Shading Mode"},"sceneLighting":true,"audioPlay":false,"sceneViewState":{"showFog":true,"showMaterialUpdate":false,"showSkybox":true,"showFlares":true,"showImageEffects":true,"showParticleSystems":true},"in2DMode":false,"pivot":{"x":37.35174560546875,"y":8.386911392211914,"z":7.471053123474121},"rotation":{"x":-0.27687662839889529,"y":0.48707547783851626,"z":-0.16619305312633515,"w":-0.8114657998085022},"size":43.80721664428711,"orthographic":false}